sftpgo_client/__init__.py
sftpgo_client/py.typed
sftpgo_client/base/__init__.py
sftpgo_client/base/client.py
sftpgo_client/base/types.py
sftpgo_client/base/api/__init__.py
sftpgo_client/base/api/admins/__init__.py
sftpgo_client/base/api/admins/add_admin.py
sftpgo_client/base/api/admins/admin_forgot_password.py
sftpgo_client/base/api/admins/admin_reset_password.py
sftpgo_client/base/api/admins/change_admin_password.py
sftpgo_client/base/api/admins/change_admin_password_deprecated.py
sftpgo_client/base/api/admins/delete_admin.py
sftpgo_client/base/api/admins/disable_admin_2fa.py
sftpgo_client/base/api/admins/generate_admin_recovery_codes.py
sftpgo_client/base/api/admins/generate_admin_totp_secret.py
sftpgo_client/base/api/admins/get_admin_by_username.py
sftpgo_client/base/api/admins/get_admin_profile.py
sftpgo_client/base/api/admins/get_admin_recovery_codes.py
sftpgo_client/base/api/admins/get_admin_totp_configs.py
sftpgo_client/base/api/admins/get_admins.py
sftpgo_client/base/api/admins/save_admin_totp_config.py
sftpgo_client/base/api/admins/update_admin.py
sftpgo_client/base/api/admins/update_admin_profile.py
sftpgo_client/base/api/admins/validate_admin_totp_secret.py
sftpgo_client/base/api/api_keys/__init__.py
sftpgo_client/base/api/api_keys/add_api_key.py
sftpgo_client/base/api/api_keys/delete_api_key.py
sftpgo_client/base/api/api_keys/get_api_key_by_id.py
sftpgo_client/base/api/api_keys/get_api_keys.py
sftpgo_client/base/api/api_keys/update_api_key.py
sftpgo_client/base/api/connections/__init__.py
sftpgo_client/base/api/connections/close_connection.py
sftpgo_client/base/api/connections/get_connections.py
sftpgo_client/base/api/data_retention/__init__.py
sftpgo_client/base/api/data_retention/get_users_retention_checks.py
sftpgo_client/base/api/data_retention/start_user_retention_check.py
sftpgo_client/base/api/defender/__init__.py
sftpgo_client/base/api/defender/delete_defender_host_by_id.py
sftpgo_client/base/api/defender/get_ban_time.py
sftpgo_client-0.3.1.dist-info/LICENSE
sftpgo_client-0.3.1.dist-info/METADATA
sftpgo_client-0.3.1.dist-info/WHEEL
sftpgo_client-0.3.1.dist-info/top_level.txt
sftpgo_client-0.3.1.dist-info/RECORD
