Metadata-Version: 2.1
Name: sftpgo-client
Version: 0.3.1
Summary: Python client for the SFTPGo API
Home-page: https://github.com/ramnes/sftpgo-client
Author: Guillaume Gelin
Author-email: contact@ramnes.eu
License: UNKNOWN
Platform: UNKNOWN
Requires-Python: >=3.6, <4
License-File: LICENSE
Requires-Dist: httpx (<0.18.0,>=0.15.0)
Requires-Dist: attrs (>=20.1.0)
Requires-Dist: python-dateutil (<3,>=2.8.0)
